setup.py
py_salt.egg-info/PKG-INFO
py_salt.egg-info/SOURCES.txt
py_salt.egg-info/dependency_links.txt
py_salt.egg-info/top_level.txt
pysalt/__init__.py