Metadata-Version: 1.0
Name: py-salt
Version: 1.0
Summary: Get pillar and grains data on salt.
Home-page: UNKNOWN
Author: Alexey Dubkov
Author-email: alexey.dubkov@gmail.com
License: UNKNOWN
Platform: UNKNOWN
